[
  {
    "id": "9761",
    "position": "1",
    "barPosition": 1,
    "bar": 120,
    "vbar": 0,
    "vbarPosition": 0,
    "lbar": 0,
    "lbarPosition": 0,
    "jbar": 0,
    "jbarPosition": 0,
    "rbar": 0,
    "rbarPosition": 0,
    "name": "Dan Meggison",
    "gender": "Male",
    "category": "Senior",
    "club": "GS Metro",
    "time": "0:55:49",
    "speed": "26.87 Mph",
    "standard": "",
    "onStandard": ""
  },
  {
    "id": "317",
    "position": "2",
    "barPosition": 2,
    "bar": 119,
    "vbar": 118,
    "vbarPosition": 3,
    "lbar": 0,
    "lbarPosition": 0,
    "jbar": 0,
    "jbarPosition": 0,
    "rbar": 0,
    "rbarPosition": 0,
    "name": "Phil Hall",
    "gender": "Male",
    "category": "Vet",
    "club": "Breeze Bikes RT",
    "time": "0:57:20",
    "speed": "26.16 Mph",
    "standard": "01:06:51",
    "onStandard": "-00:09:31"
  },
  {
    "id": "4064",
    "position": "3",
    "barPosition": 3,
    "bar": 118,
    "vbar": 0,
    "vbarPosition": 0,
    "lbar": 0,
    "lbarPosition": 0,
    "jbar": 0,
    "jbarPosition": 0,
    "rbar": 120,
    "rbarPosition": 1,
    "name": "Mark Robertson",
    "gender": "Male",
    "category": "Senior",
    "club": "Army Cycling Union",
    "time": "0:57:43",
    "speed": "25.99 Mph",
    "standard": "",
    "onStandard": ""
  },
  {
    "id": "18199",
    "position": "4",
    "barPosition": 4,
    "bar": 117,
    "vbar": 0,
    "vbarPosition": 0,
    "lbar": 0,
    "lbarPosition": 0,
    "jbar": 0,
    "jbarPosition": 0,
    "rbar": 0,
    "rbarPosition": 0,
    "name": "Julian Macbride",
    "gender": "Male",
    "category": "Senior",
    "club": "Blaydon CC",
    "time": "0:58:03",
    "speed": "25.84 Mph",
    "standard": "",
    "onStandard": ""
  },
  {
    "id": "1033",
    "position": "5",
    "barPosition": 5,
    "bar": 116,
    "vbar": 0,
    "vbarPosition": 0,
    "lbar": 0,
    "lbarPosition": 0,
    "jbar": 0,
    "jbarPosition": 0,
    "rbar": 0,
    "rbarPosition": 0,
    "name": "Steven Craggs",
    "gender": "Male",
    "category": "Senior",
    "club": "Blaydon CC",
    "time": "0:58:16",
    "speed": "25.74 Mph",
    "standard": "",
    "onStandard": ""
  },
  {
    "id": "6124",
    "position": "6",
    "barPosition": 6,
    "bar": 115,
    "vbar": 119,
    "vbarPosition": 2,
    "lbar": 0,
    "lbarPosition": 0,
    "jbar": 0,
    "jbarPosition": 0,
    "rbar": 0,
    "rbarPosition": 0,
    "name": "Ian Norris",
    "gender": "Male",
    "category": "Vet",
    "club": "Blumilk.com",
    "time": "0:58:23",
    "speed": "25.69 Mph",
    "standard": "01:08:26",
    "onStandard": "-00:10:03"
  },
  {
    "id": "3377",
    "position": "7",
    "barPosition": 7,
    "bar": 114,
    "vbar": 0,
    "vbarPosition": 0,
    "lbar": 0,
    "lbarPosition": 0,
    "jbar": 0,
    "jbarPosition": 0,
    "rbar": 0,
    "rbarPosition": 0,
    "name": "John Routledge",
    "gender": "Male",
    "category": "Senior",
    "club": "Barnesbury CC",
    "time": "0:58:33",
    "speed": "25.62 Mph",
    "standard": "",
    "onStandard": ""
  },
  {
    "id": "866",
    "position": "8",
    "barPosition": 8,
    "bar": 113,
    "vbar": 117,
    "vbarPosition": 4,
    "lbar": 0,
    "lbarPosition": 0,
    "jbar": 0,
    "jbarPosition": 0,
    "rbar": 0,
    "rbarPosition": 0,
    "name": "Colin Atkinson",
    "gender": "Male",
    "category": "Vet",
    "club": "Muckle Cycle Club",
    "time": "0:58:49",
    "speed": "25.50 Mph",
    "standard": "01:08:14",
    "onStandard": "-00:09:25"
  },
  {
    "id": "5439",
    "position": "9",
    "barPosition": 9,
    "bar": 112,
    "vbar": 0,
    "vbarPosition": 0,
    "lbar": 0,
    "lbarPosition": 0,
    "jbar": 0,
    "jbarPosition": 0,
    "rbar": 0,
    "rbarPosition": 0,
    "name": "Jamie Johnson",
    "gender": "Male",
    "category": "Senior",
    "club": "Barnesbury CC",
    "time": "0:59:19",
    "speed": "25.29 Mph",
    "standard": "",
    "onStandard": ""
  },
  {
    "id": "705",
    "position": "10",
    "barPosition": 10,
    "bar": 111,
    "vbar": 120,
    "vbarPosition": 1,
    "lbar": 0,
    "lbarPosition": 0,
    "jbar": 0,
    "jbarPosition": 0,
    "rbar": 0,
    "rbarPosition": 0,
    "name": "Nev Martin",
    "gender": "Male",
    "category": "Vet",
    "club": "GS Metro",
    "time": "0:59:43",
    "speed": "25.12 Mph",
    "standard": "01:10:04",
    "onStandard": "-00:10:21"
  },
  {
    "id": "942",
    "position": "11",
    "barPosition": 0,
    "bar": 0,
    "vbar": 0,
    "vbarPosition": 0,
    "lbar": 0,
    "lbarPosition": 0,
    "jbar": 0,
    "jbarPosition": 0,
    "rbar": 0,
    "rbarPosition": 0,
    "name": "Russ Richardson",
    "gender": "Male",
    "category": "Vet",
    "club": "Teesdale CRC",
    "time": "1:00:22",
    "speed": "24.85 Mph",
    "standard": "",
    "onStandard": ""
  },
  {
    "id": "2727",
    "position": "12",
    "barPosition": 11,
    "bar": 110,
    "vbar": 116,
    "vbarPosition": 5,
    "lbar": 0,
    "lbarPosition": 0,
    "jbar": 0,
    "jbarPosition": 0,
    "rbar": 0,
    "rbarPosition": 0,
    "name": "Wayne Coates",
    "gender": "Male",
    "category": "Vet",
    "club": "Derwentside CC",
    "time": "1:01:15",
    "speed": "24.49 Mph",
    "standard": "01:10:04",
    "onStandard": "-00:08:49"
  },
  {
    "id": "246",
    "position": "13",
    "barPosition": 12,
    "bar": 109,
    "vbar": 115,
    "vbarPosition": 6,
    "lbar": 0,
    "lbarPosition": 0,
    "jbar": 0,
    "jbarPosition": 0,
    "rbar": 0,
    "rbarPosition": 0,
    "name": "Mark Herbert",
    "gender": "Male",
    "category": "Vet",
    "club": "Derwentside CC",
    "time": "1:01:17",
    "speed": "24.48 Mph",
    "standard": "01:08:14",
    "onStandard": "-00:06:57"
  },
  {
    "id": "18333",
    "position": "14",
    "barPosition": 13,
    "bar": 108,
    "vbar": 0,
    "vbarPosition": 0,
    "lbar": 0,
    "lbarPosition": 0,
    "jbar": 0,
    "jbarPosition": 0,
    "rbar": 0,
    "rbarPosition": 0,
    "name": "Peter Stokoe",
    "gender": "Male",
    "category": "Senior",
    "club": "Sunderland Clarion",
    "time": "1:01:43",
    "speed": "24.30 Mph",
    "standard": "",
    "onStandard": ""
  },
  {
    "id": "446",
    "position": "15",
    "barPosition": 14,
    "bar": 107,
    "vbar": 114,
    "vbarPosition": 7,
    "lbar": 0,
    "lbarPosition": 0,
    "jbar": 0,
    "jbarPosition": 0,
    "rbar": 119,
    "rbarPosition": 2,
    "name": "Paul Hague",
    "gender": "Male",
    "category": "Vet",
    "club": "Gosforth RC",
    "time": "1:01:54",
    "speed": "24.23 Mph",
    "standard": "01:08:14",
    "onStandard": "-00:06:20"
  },
  {
    "id": "1770",
    "position": "16",
    "barPosition": 15,
    "bar": 106,
    "vbar": 113,
    "vbarPosition": 8,
    "lbar": 0,
    "lbarPosition": 0,
    "jbar": 0,
    "jbarPosition": 0,
    "rbar": 0,
    "rbarPosition": 0,
    "name": "Brian Johnson",
    "gender": "Male",
    "category": "Vet",
    "club": "Reifen Racing",
    "time": "1:02:15",
    "speed": "24.10 Mph",
    "standard": "01:08:26",
    "onStandard": "-00:06:11"
  },
  {
    "id": "6029",
    "position": "17",
    "barPosition": 16,
    "bar": 105,
    "vbar": 112,
    "vbarPosition": 9,
    "lbar": 0,
    "lbarPosition": 0,
    "jbar": 0,
    "jbarPosition": 0,
    "rbar": 0,
    "rbarPosition": 0,
    "name": "Peter Herdman",
    "gender": "Male",
    "category": "Vet",
    "club": "Blaydon CC",
    "time": "1:02:25",
    "speed": "24.03 Mph",
    "standard": "01:07:26",
    "onStandard": "-00:05:01"
  },
  {
    "id": "15865",
    "position": "18",
    "barPosition": 0,
    "bar": 0,
    "vbar": 0,
    "vbarPosition": 0,
    "lbar": 0,
    "lbarPosition": 0,
    "jbar": 0,
    "jbarPosition": 0,
    "rbar": 0,
    "rbarPosition": 0,
    "name": "David Linsley",
    "gender": "Male",
    "category": "Vet",
    "club": "Tyne & Wear Fire & Rescue Service CC",
    "time": "1:03:36",
    "speed": "23.58 Mph",
    "standard": "",
    "onStandard": ""
  },
  {
    "id": "5444",
    "position": "19",
    "barPosition": 17,
    "bar": 104,
    "vbar": 107,
    "vbarPosition": 14,
    "lbar": 0,
    "lbarPosition": 0,
    "jbar": 0,
    "jbarPosition": 0,
    "rbar": 0,
    "rbarPosition": 0,
    "name": "Lee Statham",
    "gender": "Male",
    "category": "Vet",
    "club": "Houghton CC",
    "time": "1:04:37",
    "speed": "23.21 Mph",
    "standard": "01:06:39",
    "onStandard": "-00:02:02"
  },
  {
    "id": "13754",
    "position": "20",
    "barPosition": 18,
    "bar": 103,
    "vbar": 103,
    "vbarPosition": 18,
    "lbar": 0,
    "lbarPosition": 0,
    "jbar": 0,
    "jbarPosition": 0,
    "rbar": 118,
    "rbarPosition": 3,
    "name": "Stephen Walton",
    "gender": "Male",
    "category": "Vet",
    "club": "Muckle Cycle Club",
    "time": "1:04:59",
    "speed": "23.08 Mph",
    "standard": "01:06:13",
    "onStandard": "-00:01:14"
  },
  {
    "id": "923",
    "position": "21",
    "barPosition": 19,
    "bar": 102,
    "vbar": 108,
    "vbarPosition": 13,
    "lbar": 0,
    "lbarPosition": 0,
    "jbar": 0,
    "jbarPosition": 0,
    "rbar": 0,
    "rbarPosition": 0,
    "name": "Neil Parkin",
    "gender": "Male",
    "category": "Vet",
    "club": "Derwentside CC",
    "time": "1:05:00",
    "speed": "23.08 Mph",
    "standard": "01:07:03",
    "onStandard": "-00:02:03"
  },
  {
    "id": "19486",
    "position": "22",
    "barPosition": 20,
    "bar": 101,
    "vbar": 105,
    "vbarPosition": 16,
    "lbar": 0,
    "lbarPosition": 0,
    "jbar": 0,
    "jbarPosition": 0,
    "rbar": 0,
    "rbarPosition": 0,
    "name": "Mark Whaley",
    "gender": "Male",
    "category": "Vet",
    "club": "Blaydon CC",
    "time": "1:05:37",
    "speed": "22.86 Mph",
    "standard": "01:07:26",
    "onStandard": "-00:01:49"
  },
  {
    "id": "18735",
    "position": "22",
    "barPosition": 20,
    "bar": 101,
    "vbar": 0,
    "vbarPosition": 0,
    "lbar": 0,
    "lbarPosition": 0,
    "jbar": 0,
    "jbarPosition": 0,
    "rbar": 117,
    "rbarPosition": 4,
    "name": "James George Dunn",
    "gender": "Male",
    "category": "Senior",
    "club": "South Shields Velo Cycling Club",
    "time": "1:05:37",
    "speed": "22.86 Mph",
    "standard": "",
    "onStandard": ""
  },
  {
    "id": "7233",
    "position": "24",
    "barPosition": 0,
    "bar": 0,
    "vbar": 0,
    "vbarPosition": 0,
    "lbar": 0,
    "lbarPosition": 0,
    "jbar": 0,
    "jbarPosition": 0,
    "rbar": 0,
    "rbarPosition": 0,
    "name": "Bill Maxwell",
    "gender": "Male",
    "category": "Vet",
    "club": "Border City Whs CC",
    "time": "1:05:50",
    "speed": "22.78 Mph",
    "standard": "",
    "onStandard": ""
  },
  {
    "id": "293",
    "position": "25",
    "barPosition": 22,
    "bar": 99,
    "vbar": 109,
    "vbarPosition": 12,
    "lbar": 0,
    "lbarPosition": 0,
    "jbar": 0,
    "jbarPosition": 0,
    "rbar": 0,
    "rbarPosition": 0,
    "name": "Jock Bolam",
    "gender": "Male",
    "category": "Vet",
    "club": "Breeze Bikes RT",
    "time": "1:05:52",
    "speed": "22.77 Mph",
    "standard": "01:08:02",
    "onStandard": "-00:02:10"
  },
  {
    "id": "18204",
    "position": "26",
    "barPosition": 23,
    "bar": 98,
    "vbar": 0,
    "vbarPosition": 0,
    "lbar": 120,
    "lbarPosition": 1,
    "jbar": 0,
    "jbarPosition": 0,
    "rbar": 0,
    "rbarPosition": 0,
    "name": "Joanne Rea",
    "gender": "Female",
    "category": "Senior",
    "club": "Blaydon CC",
    "time": "1:06:05",
    "speed": "22.70 Mph",
    "standard": "",
    "onStandard": ""
  },
  {
    "id": "24566",
    "position": "27",
    "barPosition": 0,
    "bar": 0,
    "vbar": 0,
    "vbarPosition": 0,
    "lbar": 0,
    "lbarPosition": 0,
    "jbar": 0,
    "jbarPosition": 0,
    "rbar": 0,
    "rbarPosition": 0,
    "name": "Terry Parvin",
    "gender": "Male",
    "category": "Vet",
    "club": "Ferryhill Whs",
    "time": "1:06:19",
    "speed": "22.62 Mph",
    "standard": "",
    "onStandard": ""
  },
  {
    "id": "708",
    "position": "28",
    "barPosition": 24,
    "bar": 97,
    "vbar": 0,
    "vbarPosition": 0,
    "lbar": 0,
    "lbarPosition": 0,
    "jbar": 0,
    "jbarPosition": 0,
    "rbar": 116,
    "rbarPosition": 5,
    "name": "Christopher Beaty",
    "gender": "Male",
    "category": "Senior",
    "club": "Allen Valley Velo",
    "time": "1:06:30",
    "speed": "22.56 Mph",
    "standard": "",
    "onStandard": ""
  },
  {
    "id": "2760",
    "position": "29",
    "barPosition": 0,
    "bar": 0,
    "vbar": 0,
    "vbarPosition": 0,
    "lbar": 0,
    "lbarPosition": 0,
    "jbar": 0,
    "jbarPosition": 0,
    "rbar": 0,
    "rbarPosition": 0,
    "name": "Richard Tyson",
    "gender": "Male",
    "category": "Vet",
    "club": "Rock to Roll CC",
    "time": "1:06:39",
    "speed": "22.51 Mph",
    "standard": "",
    "onStandard": ""
  },
  {
    "id": "7727",
    "position": "30",
    "barPosition": 0,
    "bar": 0,
    "vbar": 0,
    "vbarPosition": 0,
    "lbar": 0,
    "lbarPosition": 0,
    "jbar": 0,
    "jbarPosition": 0,
    "rbar": 0,
    "rbarPosition": 0,
    "name": "Natalie Batey",
    "gender": "Female",
    "category": "Senior",
    "club": "Tyne & Wear Fire & Rescue Service CC",
    "time": "1:06:42",
    "speed": "22.49 Mph",
    "standard": "",
    "onStandard": ""
  },
  {
    "id": "3838",
    "position": "31",
    "barPosition": 25,
    "bar": 96,
    "vbar": 0,
    "vbarPosition": 0,
    "lbar": 119,
    "lbarPosition": 2,
    "jbar": 0,
    "jbarPosition": 0,
    "rbar": 0,
    "rbarPosition": 0,
    "name": "Gemma Hutchins",
    "gender": "Female",
    "category": "Senior",
    "club": "Blaydon CC",
    "time": "1:07:01",
    "speed": "22.38 Mph",
    "standard": "",
    "onStandard": ""
  },
  {
    "id": "17551",
    "position": "32",
    "barPosition": 26,
    "bar": 95,
    "vbar": 102,
    "vbarPosition": 19,
    "lbar": 0,
    "lbarPosition": 0,
    "jbar": 0,
    "jbarPosition": 0,
    "rbar": 115,
    "rbarPosition": 6,
    "name": "Michael Aspey",
    "gender": "Male",
    "category": "Vet",
    "club": "Northumbria Police C.C.",
    "time": "1:07:30",
    "speed": "22.22 Mph",
    "standard": "01:08:14",
    "onStandard": "-00:00:44"
  },
  {
    "id": "5305",
    "position": "33",
    "barPosition": 27,
    "bar": 94,
    "vbar": 100,
    "vbarPosition": 21,
    "lbar": 0,
    "lbarPosition": 0,
    "jbar": 0,
    "jbarPosition": 0,
    "rbar": 114,
    "rbarPosition": 7,
    "name": "Ian Gallon",
    "gender": "Male",
    "category": "Vet",
    "club": "North Tyneside Riders CC",
    "time": "1:07:35",
    "speed": "22.19 Mph",
    "standard": "01:08:02",
    "onStandard": "-00:00:27"
  },
  {
    "id": "1799",
    "position": "34",
    "barPosition": 28,
    "bar": 93,
    "vbar": 111,
    "vbarPosition": 10,
    "lbar": 118,
    "lbarPosition": 3,
    "jbar": 0,
    "jbarPosition": 0,
    "rbar": 0,
    "rbarPosition": 0,
    "name": "Carrie Brookes",
    "gender": "Female",
    "category": "Vet",
    "club": "North Tyneside Riders CC",
    "time": "1:07:56",
    "speed": "22.08 Mph",
    "standard": "01:11:56",
    "onStandard": "-00:04:00"
  },
  {
    "id": "18842",
    "position": "35",
    "barPosition": 29,
    "bar": 92,
    "vbar": 99,
    "vbarPosition": 22,
    "lbar": 0,
    "lbarPosition": 0,
    "jbar": 0,
    "jbarPosition": 0,
    "rbar": 0,
    "rbarPosition": 0,
    "name": "Martin Rasmussen",
    "gender": "Male",
    "category": "Vet",
    "club": "Tyneside Vagabonds CC",
    "time": "1:07:57",
    "speed": "22.08 Mph",
    "standard": "01:08:02",
    "onStandard": "-00:00:05"
  },
  {
    "id": "5296",
    "position": "36",
    "barPosition": 30,
    "bar": 91,
    "vbar": 97,
    "vbarPosition": 24,
    "lbar": 0,
    "lbarPosition": 0,
    "jbar": 0,
    "jbarPosition": 0,
    "rbar": 0,
    "rbarPosition": 0,
    "name": "Keith Sibbald",
    "gender": "Male",
    "category": "Vet",
    "club": "Cramlington CC",
    "time": "1:08:03",
    "speed": "22.04 Mph",
    "standard": "01:07:26",
    "onStandard": "00:00:37"
  },
  {
    "id": "8989",
    "position": "37",
    "barPosition": 31,
    "bar": 90,
    "vbar": 110,
    "vbarPosition": 11,
    "lbar": 0,
    "lbarPosition": 0,
    "jbar": 0,
    "jbarPosition": 0,
    "rbar": 0,
    "rbarPosition": 0,
    "name": "Stuart Cook",
    "gender": "Male",
    "category": "Vet",
    "club": "Cestria C.C.",
    "time": "1:08:11",
    "speed": "22.00 Mph",
    "standard": "01:10:38",
    "onStandard": "-00:02:27"
  },
  {
    "id": "24498",
    "position": "38",
    "barPosition": 32,
    "bar": 89,
    "vbar": 101,
    "vbarPosition": 20,
    "lbar": 0,
    "lbarPosition": 0,
    "jbar": 0,
    "jbarPosition": 0,
    "rbar": 0,
    "rbarPosition": 0,
    "name": "Ian Mclean",
    "gender": "Male",
    "category": "Vet",
    "club": "Tyneside Vagabonds CC",
    "time": "1:09:02",
    "speed": "21.73 Mph",
    "standard": "01:09:34",
    "onStandard": "-00:00:32"
  },
  {
    "id": "25188",
    "position": "39",
    "barPosition": 33,
    "bar": 88,
    "vbar": 94,
    "vbarPosition": 27,
    "lbar": 0,
    "lbarPosition": 0,
    "jbar": 0,
    "jbarPosition": 0,
    "rbar": 0,
    "rbarPosition": 0,
    "name": "David Simpson",
    "gender": "Male",
    "category": "Vet",
    "club": "South Shields Velo Cycling Club",
    "time": "1:09:25",
    "speed": "21.61 Mph",
    "standard": "01:06:51",
    "onStandard": "00:02:34"
  },
  {
    "id": "18682",
    "position": "40",
    "barPosition": 0,
    "bar": 0,
    "vbar": 0,
    "vbarPosition": 0,
    "lbar": 0,
    "lbarPosition": 0,
    "jbar": 0,
    "jbarPosition": 0,
    "rbar": 0,
    "rbarPosition": 0,
    "name": "Michelle Highfield",
    "gender": "Female",
    "category": "Vet",
    "club": "Berwick Wheelers Cycling Club",
    "time": "1:10:16",
    "speed": "21.35 Mph",
    "standard": "",
    "onStandard": ""
  },
  {
    "id": "4497",
    "position": "41",
    "barPosition": 34,
    "bar": 87,
    "vbar": 106,
    "vbarPosition": 15,
    "lbar": 0,
    "lbarPosition": 0,
    "jbar": 0,
    "jbarPosition": 0,
    "rbar": 0,
    "rbarPosition": 0,
    "name": "Raymond Bell",
    "gender": "Male",
    "category": "Vet",
    "club": "Derwentside CC",
    "time": "1:11:20",
    "speed": "21.03 Mph",
    "standard": "01:13:10",
    "onStandard": "-00:01:50"
  },
  {
    "id": "3419",
    "position": "42",
    "barPosition": 35,
    "bar": 86,
    "vbar": 96,
    "vbarPosition": 25,
    "lbar": 117,
    "lbarPosition": 4,
    "jbar": 0,
    "jbarPosition": 0,
    "rbar": 0,
    "rbarPosition": 0,
    "name": "Teri Bayliss",
    "gender": "Female",
    "category": "Vet",
    "club": "GS Metro",
    "time": "1:12:33",
    "speed": "20.68 Mph",
    "standard": "01:11:14",
    "onStandard": "00:01:19"
  },
  {
    "id": "16321",
    "position": "43",
    "barPosition": 36,
    "bar": 85,
    "vbar": 95,
    "vbarPosition": 26,
    "lbar": 0,
    "lbarPosition": 0,
    "jbar": 0,
    "jbarPosition": 0,
    "rbar": 0,
    "rbarPosition": 0,
    "name": "Graeme Dawson",
    "gender": "Male",
    "category": "Vet",
    "club": "Gosforth RC",
    "time": "1:12:53",
    "speed": "20.58 Mph",
    "standard": "01:10:21",
    "onStandard": "00:02:32"
  },
  {
    "id": "3953",
    "position": "43",
    "barPosition": 36,
    "bar": 85,
    "vbar": 0,
    "vbarPosition": 0,
    "lbar": 116,
    "lbarPosition": 5,
    "jbar": 0,
    "jbarPosition": 0,
    "rbar": 0,
    "rbarPosition": 0,
    "name": "Hannah Baker",
    "gender": "Female",
    "category": "Senior",
    "club": "North Tyneside Riders CC",
    "time": "1:12:53",
    "speed": "20.58 Mph",
    "standard": "",
    "onStandard": ""
  },
  {
    "id": "113",
    "position": "45",
    "barPosition": 38,
    "bar": 83,
    "vbar": 98,
    "vbarPosition": 23,
    "lbar": 115,
    "lbarPosition": 6,
    "jbar": 0,
    "jbarPosition": 0,
    "rbar": 0,
    "rbarPosition": 0,
    "name": "Sara Cummings",
    "gender": "Female",
    "category": "Vet",
    "club": "Blaydon CC",
    "time": "1:12:59",
    "speed": "20.55 Mph",
    "standard": "01:12:23",
    "onStandard": "00:00:36"
  },
  {
    "id": "10722",
    "position": "46",
    "barPosition": 39,
    "bar": 82,
    "vbar": 0,
    "vbarPosition": 0,
    "lbar": 114,
    "lbarPosition": 7,
    "jbar": 0,
    "jbarPosition": 0,
    "rbar": 113,
    "rbarPosition": 8,
    "name": "Jen Mcmahon",
    "gender": "Female",
    "category": "Senior",
    "club": "Muckle Cycle Club",
    "time": "1:13:19",
    "speed": "20.46 Mph",
    "standard": "",
    "onStandard": ""
  },
  {
    "id": "7500",
    "position": "47",
    "barPosition": 40,
    "bar": 81,
    "vbar": 91,
    "vbarPosition": 30,
    "lbar": 0,
    "lbarPosition": 0,
    "jbar": 0,
    "jbarPosition": 0,
    "rbar": 0,
    "rbarPosition": 0,
    "name": "Clive Rae",
    "gender": "Male",
    "category": "Vet",
    "club": "Gosforth RC",
    "time": "1:14:39",
    "speed": "20.09 Mph",
    "standard": "01:08:39",
    "onStandard": "00:06:00"
  },
  {
    "id": "2846",
    "position": "48",
    "barPosition": 41,
    "bar": 80,
    "vbar": 93,
    "vbarPosition": 28,
    "lbar": 113,
    "lbarPosition": 8,
    "jbar": 0,
    "jbarPosition": 0,
    "rbar": 0,
    "rbarPosition": 0,
    "name": "Justine Norman",
    "gender": "Female",
    "category": "Vet",
    "club": "Breeze Bikes RT",
    "time": "1:18:12",
    "speed": "19.18 Mph",
    "standard": "01:12:49",
    "onStandard": "00:05:23"
  },
  {
    "id": "15305",
    "position": "49",
    "barPosition": 42,
    "bar": 79,
    "vbar": 0,
    "vbarPosition": 0,
    "lbar": 112,
    "lbarPosition": 9,
    "jbar": 120,
    "jbarPosition": 1,
    "rbar": 0,
    "rbarPosition": 0,
    "name": "Maddy Hall",
    "gender": "Female",
    "category": "Juvenile",
    "club": "Breeze Bikes RT",
    "time": "1:18:40",
    "speed": "19.07 Mph",
    "standard": "",
    "onStandard": ""
  },
  {
    "id": "19288",
    "position": "50",
    "barPosition": 43,
    "bar": 78,
    "vbar": 104,
    "vbarPosition": 17,
    "lbar": 0,
    "lbarPosition": 0,
    "jbar": 0,
    "jbarPosition": 0,
    "rbar": 0,
    "rbarPosition": 0,
    "name": "Ronnie Thompson",
    "gender": "Male",
    "category": "Vet",
    "club": "Derwentside CC",
    "time": "1:19:22",
    "speed": "18.90 Mph",
    "standard": "01:21:02",
    "onStandard": "-00:01:40"
  },
  {
    "id": "11392",
    "position": "51",
    "barPosition": 44,
    "bar": 77,
    "vbar": 92,
    "vbarPosition": 29,
    "lbar": 111,
    "lbarPosition": 10,
    "jbar": 0,
    "jbarPosition": 0,
    "rbar": 112,
    "rbarPosition": 9,
    "name": "Sheena Harrison",
    "gender": "Female",
    "category": "Vet",
    "club": "Allen Valley Velo",
    "time": "1:19:39",
    "speed": "18.83 Mph",
    "standard": "01:14:09",
    "onStandard": "00:05:30"
  },
  {
    "id": "19158",
    "position": "52",
    "barPosition": 45,
    "bar": 76,
    "vbar": 90,
    "vbarPosition": 31,
    "lbar": 110,
    "lbarPosition": 11,
    "jbar": 0,
    "jbarPosition": 0,
    "rbar": 0,
    "rbarPosition": 0,
    "name": "Caroline Golightly",
    "gender": "Female",
    "category": "Vet",
    "club": "Sunderland Clarion",
    "time": "1:20:06",
    "speed": "18.73 Mph",
    "standard": "01:12:36",
    "onStandard": "00:07:30"
  },
  {
    "id": "19057",
    "position": "53",
    "barPosition": 0,
    "bar": 0,
    "vbar": 0,
    "vbarPosition": 0,
    "lbar": 0,
    "lbarPosition": 0,
    "jbar": 0,
    "jbarPosition": 0,
    "rbar": 0,
    "rbarPosition": 0,
    "name": "Nicola Mccoy",
    "gender": "Female",
    "category": "Vet",
    "club": "Sporting Club Gothic",
    "time": "1:21:38",
    "speed": "18.37 Mph",
    "standard": "",
    "onStandard": ""
  },
  {
    "id": "9329",
    "position": "54",
    "barPosition": 46,
    "bar": 75,
    "vbar": 89,
    "vbarPosition": 32,
    "lbar": 109,
    "lbarPosition": 12,
    "jbar": 0,
    "jbarPosition": 0,
    "rbar": 0,
    "rbarPosition": 0,
    "name": "Jane Massey",
    "gender": "Female",
    "category": "Vet",
    "club": "Cramlington CC",
    "time": "1:23:19",
    "speed": "18.00 Mph",
    "standard": "01:12:49",
    "onStandard": "00:10:30"
  },
  {
    "id": "2927",
    "position": "55",
    "barPosition": 47,
    "bar": 74,
    "vbar": 88,
    "vbarPosition": 33,
    "lbar": 0,
    "lbarPosition": 0,
    "jbar": 0,
    "jbarPosition": 0,
    "rbar": 111,
    "rbarPosition": 10,
    "name": "Gareth Davies",
    "gender": "Male",
    "category": "Vet",
    "club": "Barnesbury CC",
    "time": "1:35:08",
    "speed": "15.77 Mph",
    "standard": "01:09:34",
    "onStandard": "00:25:34"
  },
  {
    "id": "24801",
    "position": "DNF",
    "barPosition": 0,
    "bar": 0,
    "vbar": 0,
    "vbarPosition": 0,
    "lbar": 0,
    "lbarPosition": 0,
    "jbar": 0,
    "jbarPosition": 0,
    "rbar": 0,
    "rbarPosition": 0,
    "name": "Mike Donnelly",
    "gender": "Male",
    "category": "Vet",
    "club": "South Shields Velo Cycling Club",
    "time": "",
    "speed": "",
    "standard": "",
    "onStandard": ""
  },
  {
    "id": "964",
    "position": "DNF",
    "barPosition": 0,
    "bar": 0,
    "vbar": 0,
    "vbarPosition": 0,
    "lbar": 0,
    "lbarPosition": 0,
    "jbar": 0,
    "jbarPosition": 0,
    "rbar": 0,
    "rbarPosition": 0,
    "name": "Paul Mitchell",
    "gender": "Male",
    "category": "Vet",
    "club": "Blaydon CC",
    "time": "",
    "speed": "",
    "standard": "",
    "onStandard": ""
  },
  {
    "id": "1636",
    "position": "DNS",
    "barPosition": 0,
    "bar": 0,
    "vbar": 0,
    "vbarPosition": 0,
    "lbar": 0,
    "lbarPosition": 0,
    "jbar": 0,
    "jbarPosition": 0,
    "rbar": 0,
    "rbarPosition": 0,
    "name": "Patrick Deane",
    "gender": "Male",
    "category": "Vet",
    "club": "Tyneside Vagabonds CC",
    "time": "",
    "speed": "",
    "standard": "",
    "onStandard": ""
  },
  {
    "id": "7211",
    "position": "DNS",
    "barPosition": 0,
    "bar": 0,
    "vbar": 0,
    "vbarPosition": 0,
    "lbar": 0,
    "lbarPosition": 0,
    "jbar": 0,
    "jbarPosition": 0,
    "rbar": 0,
    "rbarPosition": 0,
    "name": "Neil Harrison",
    "gender": "Male",
    "category": "Vet",
    "club": "Allen Valley Velo",
    "time": "",
    "speed": "",
    "standard": "",
    "onStandard": ""
  },
  {
    "id": "1171",
    "position": "DNS",
    "barPosition": 0,
    "bar": 0,
    "vbar": 0,
    "vbarPosition": 0,
    "lbar": 0,
    "lbarPosition": 0,
    "jbar": 0,
    "jbarPosition": 0,
    "rbar": 0,
    "rbarPosition": 0,
    "name": "Peter Mcewan",
    "gender": "Male",
    "category": "Vet",
    "club": "Breeze Bikes RT",
    "time": "",
    "speed": "",
    "standard": "",
    "onStandard": ""
  },
  {
    "id": "16184",
    "position": "DNS",
    "barPosition": 0,
    "bar": 0,
    "vbar": 0,
    "vbarPosition": 0,
    "lbar": 0,
    "lbarPosition": 0,
    "jbar": 0,
    "jbarPosition": 0,
    "rbar": 0,
    "rbarPosition": 0,
    "name": "Gemma Frost",
    "gender": "Female",
    "category": "Senior",
    "club": "Team Swift",
    "time": "",
    "speed": "",
    "standard": "",
    "onStandard": ""
  },
  {
    "id": "554",
    "position": "DNS",
    "barPosition": 0,
    "bar": 0,
    "vbar": 0,
    "vbarPosition": 0,
    "lbar": 0,
    "lbarPosition": 0,
    "jbar": 0,
    "jbarPosition": 0,
    "rbar": 0,
    "rbarPosition": 0,
    "name": "Andrew Hall",
    "gender": "Male",
    "category": "Senior",
    "club": "GS Metro",
    "time": "",
    "speed": "",
    "standard": "",
    "onStandard": ""
  },
  {
    "id": "9684",
    "position": "DNS",
    "barPosition": 0,
    "bar": 0,
    "vbar": 0,
    "vbarPosition": 0,
    "lbar": 0,
    "lbarPosition": 0,
    "jbar": 0,
    "jbarPosition": 0,
    "rbar": 0,
    "rbarPosition": 0,
    "name": "Darren Williamson",
    "gender": "Male",
    "category": "Vet",
    "club": "Muckle Cycle Club",
    "time": "",
    "speed": "",
    "standard": "",
    "onStandard": ""
  },
  {
    "id": "8466",
    "position": "DNS",
    "barPosition": 0,
    "bar": 0,
    "vbar": 0,
    "vbarPosition": 0,
    "lbar": 0,
    "lbarPosition": 0,
    "jbar": 0,
    "jbarPosition": 0,
    "rbar": 0,
    "rbarPosition": 0,
    "name": "Murray Doyle",
    "gender": "Male",
    "category": "Vet",
    "club": "Bute Wheelers",
    "time": "",
    "speed": "",
    "standard": "",
    "onStandard": ""
  },
  {
    "id": "17279",
    "position": "DNS",
    "barPosition": 0,
    "bar": 0,
    "vbar": 0,
    "vbarPosition": 0,
    "lbar": 0,
    "lbarPosition": 0,
    "jbar": 0,
    "jbarPosition": 0,
    "rbar": 0,
    "rbarPosition": 0,
    "name": "Kerry Gowland",
    "gender": "Female",
    "category": "Vet",
    "club": "Houghton CC",
    "time": "",
    "speed": "",
    "standard": "",
    "onStandard": ""
  },
  {
    "id": "92",
    "position": "DNS",
    "barPosition": 0,
    "bar": 0,
    "vbar": 0,
    "vbarPosition": 0,
    "lbar": 0,
    "lbarPosition": 0,
    "jbar": 0,
    "jbarPosition": 0,
    "rbar": 0,
    "rbarPosition": 0,
    "name": "Mick Chappel",
    "gender": "Male",
    "category": "Vet",
    "club": "North Tyneside Riders CC",
    "time": "",
    "speed": "",
    "standard": "",
    "onStandard": ""
  },
  {
    "id": "5896",
    "position": "DNS",
    "barPosition": 0,
    "bar": 0,
    "vbar": 0,
    "vbarPosition": 0,
    "lbar": 0,
    "lbarPosition": 0,
    "jbar": 0,
    "jbarPosition": 0,
    "rbar": 0,
    "rbarPosition": 0,
    "name": "Colin Gardener",
    "gender": "Male",
    "category": "Vet",
    "club": "Flyte Racing",
    "time": "",
    "speed": "",
    "standard": "",
    "onStandard": ""
  },
  {
    "id": "16334",
    "position": "DNS",
    "barPosition": 0,
    "bar": 0,
    "vbar": 0,
    "vbarPosition": 0,
    "lbar": 0,
    "lbarPosition": 0,
    "jbar": 0,
    "jbarPosition": 0,
    "rbar": 0,
    "rbarPosition": 0,
    "name": "Danny Wilcox",
    "gender": "Male",
    "category": "Vet",
    "club": "North Tyneside Riders CC",
    "time": "",
    "speed": "",
    "standard": "",
    "onStandard": ""
  }
]