{
  "id": "1428",
  "name": "Stephen Cummings",
  "sex": "Male",
  "category": "Vet",
  "club": "Blaydon CC",
  "bar": {
    "short": [],
    "medium": [],
    "long": [],
    "shortCount": 0,
    "mediumCount": 0,
    "longCount": 0,
    "allCount": 0,
    "complete": false,
    "canComplete": false,
    "averagePointsPerShortRace": 0,
    "averagePointsPerMediumRace": 0,
    "averagePointsPerLongRace": 0,
    "averagePointsPerRace": 0,
    "remainingShortPoints": 240,
    "remainingMediumPoints": 360,
    "remainingLongPoints": 120,
    "remainingPoints": 720,
    "predictedFinalPoints": 0,
    "pointsDirection": 0,
    "regionalChampionship": {
      "raced": 0,
      "totalPoints": 0
    },
    "tieBreak": {
      "raced": 0,
      "totalPoints": 0
    },
    "totals": {
      "short": 0,
      "medium": 0,
      "long": 0,
      "grand": 0
    },
    "tags": [
      {
        "cssclass": "tag is-black",
        "text": "1 x DNS"
      }
    ],
    "currentPosition": 288,
    "rivals": [
      {
        "position": 1,
        "id": "3625",
        "pointsDirection": 0,
        "barPredictedFinalPosition": 1,
        "name": "Adam Wild",
        "club": "GS Metro",
        "averagePointsPerRace": 119.83333333333333,
        "predictedFinalPoints": 719,
        "grandTotal": 719,
        "complete": true,
        "canComplete": true,
        "regionalChampionshipPoints": 240,
        "tieBreakPoints": 239
      },
      {
        "position": 285,
        "id": "22623",
        "pointsDirection": 0,
        "name": "Craig Foley",
        "club": "Tricademy",
        "averagePointsPerRace": 0,
        "predictedFinalPoints": 0,
        "grandTotal": 0,
        "complete": false,
        "canComplete": false,
        "regionalChampionshipPoints": 0,
        "tieBreakPoints": 0
      },
      {
        "position": 286,
        "id": "391",
        "pointsDirection": 0,
        "name": "Richard Cleathero",
        "club": "North Racing",
        "averagePointsPerRace": 0,
        "predictedFinalPoints": 0,
        "grandTotal": 0,
        "complete": false,
        "canComplete": false,
        "regionalChampionshipPoints": 0,
        "tieBreakPoints": 0
      },
      {
        "position": 287,
        "id": "24000",
        "pointsDirection": 0,
        "name": "Xanthe Polaine",
        "club": "Team Newcastle Triathlon",
        "averagePointsPerRace": 0,
        "predictedFinalPoints": 0,
        "grandTotal": 0,
        "complete": false,
        "canComplete": false,
        "regionalChampionshipPoints": 0,
        "tieBreakPoints": 0
      },
      {
        "position": 288,
        "id": "1428",
        "pointsDirection": 0,
        "name": "Stephen Cummings",
        "club": "Blaydon CC",
        "averagePointsPerRace": 0,
        "predictedFinalPoints": 0,
        "grandTotal": 0,
        "complete": false,
        "canComplete": false,
        "regionalChampionshipPoints": 0,
        "tieBreakPoints": 0
      },
      {
        "position": 289,
        "id": "9230",
        "pointsDirection": 0,
        "name": "Shaun Inglis",
        "club": "Hawick Cycling Club",
        "averagePointsPerRace": 0,
        "predictedFinalPoints": 0,
        "grandTotal": 0,
        "complete": false,
        "canComplete": false,
        "regionalChampionshipPoints": 0,
        "tieBreakPoints": 0
      },
      {
        "position": 290,
        "id": "1366",
        "pointsDirection": 0,
        "name": "David Clement",
        "club": "North Tyneside Riders CC",
        "averagePointsPerRace": 0,
        "predictedFinalPoints": 0,
        "grandTotal": 0,
        "complete": false,
        "canComplete": false,
        "regionalChampionshipPoints": 0,
        "tieBreakPoints": 0
      },
      {
        "position": 291,
        "id": "7233",
        "pointsDirection": 0,
        "name": "Bill Maxwell",
        "club": "Border City Whs CC",
        "averagePointsPerRace": 0,
        "predictedFinalPoints": 0,
        "grandTotal": 0,
        "complete": false,
        "canComplete": false,
        "regionalChampionshipPoints": 0,
        "tieBreakPoints": 0
      }
    ]
  },
  "races": [
    {
      "eventId": "17210",
      "raceCategory": "short",
      "name": "North Tyneside Riders CC",
      "course": "M102B",
      "distance": 10,
      "fee": 9,
      "date": "14 April 2018",
      "club": "Blaydon CC",
      "position": "DNS",
      "time": "",
      "standard": "",
      "onStandard": "",
      "speed": "",
      "bar": 0,
      "barPosition": 0,
      "vbar": 0,
      "vbarPosition": 0,
      "lbar": 0,
      "lbarPosition": 0,
      "jbar": 0,
      "jbarPosition": 0,
      "rbar": 0,
      "rbarPosition": 0
    }
  ]
}